imgur_downloader
tests
