Metadata-Version: 1.1
Name: imgur-downloader
Version: 0.1.9
Summary: Python script/class to download an entire Imgur album in  one go into a folder of your choice
Home-page: https://github.com/jtara1/imgur_downloader
Author: jtara1
Author-email: alex@solution10.com
License: MIT
Keywords: imgur,downloader
Platform: UNKNOWN
Classifier: Programming Language :: Python
Classifier: Programming Language :: Python :: 3.5
